rxfoundry/__init__.py
rxfoundry/clients/__init__.py
rxfoundry/clients/swifty_api/__init__.py
rxfoundry/clients/swifty_api/api_client.py
rxfoundry/clients/swifty_api/api_response.py
rxfoundry/clients/swifty_api/configuration.py
rxfoundry/clients/swifty_api/exceptions.py
rxfoundry/clients/swifty_api/py.typed
rxfoundry/clients/swifty_api/rest.py
rxfoundry/clients/swifty_api/api/__init__.py
rxfoundry/clients/swifty_api/api/async_api.py
rxfoundry/clients/swifty_api/api/code_api.py
rxfoundry/clients/swifty_api/api/default_api.py
rxfoundry/clients/swifty_api/api/fax_api.py
rxfoundry/clients/swifty_api/api/medication_api.py
rxfoundry/clients/swifty_api/api/patient_api.py
rxfoundry/clients/swifty_api/api/pharmacist_api.py
rxfoundry/clients/swifty_api/api/pharmacy_api.py
rxfoundry/clients/swifty_api/api/prescriber_api.py
rxfoundry/clients/swifty_api/api/prescription_api.py
rxfoundry/clients/swifty_api/api/task_api.py
rxfoundry/clients/swifty_api/api/tasks_api.py
rxfoundry/clients/swifty_api/api/token_api.py
rxfoundry/clients/swifty_api/api/user_api.py
rxfoundry/clients/swifty_api/api/validation_api.py
rxfoundry/clients/swifty_api/api/version_api.py
rxfoundry/clients/swifty_api/api/virtual_pharmacy_api.py
rxfoundry/clients/swifty_api/api/workflow_api.py
rxfoundry/clients/swifty_api/models/__init__.py
rxfoundry/clients/swifty_api/models/address.py
rxfoundry/clients/swifty_api/models/asynchronous_response.py
rxfoundry/clients/swifty_api/models/code.py
rxfoundry/clients/swifty_api/models/code_qualifier_code.py
rxfoundry/clients/swifty_api/models/code_type.py
rxfoundry/clients/swifty_api/models/create_patient_request.py
rxfoundry/clients/swifty_api/models/error_message.py
rxfoundry/clients/swifty_api/models/fax.py
rxfoundry/clients/swifty_api/models/formulary.py
rxfoundry/clients/swifty_api/models/insurance.py
rxfoundry/clients/swifty_api/models/medication.py
rxfoundry/clients/swifty_api/models/medication_instruction.py
rxfoundry_clients_swifty_api-0.1.1018.dist-info/METADATA
rxfoundry_clients_swifty_api-0.1.1018.dist-info/WHEEL
rxfoundry_clients_swifty_api-0.1.1018.dist-info/top_level.txt
rxfoundry_clients_swifty_api-0.1.1018.dist-info/RECORD
